Metadata-Version: 2.1
Name: izh2134
Version: 0.1
Summary: Numerical methods
Home-page: UNKNOWN
Author-email: ustinovkirill23@gmail.com
License: UNKNOWN
Platform: UNKNOWN
